Metadata-Version: 2.1
Name: odoo-addon-hr_expense_remove_mobile_link
Version: 17.0.1.0.0.2
Requires-Python: >=3.10
Requires-Dist: odoo>=17.0a,<17.1dev
Summary: Remove Odoo Enterprise mobile app download links
Home-page: https://github.com/OCA/server-brand
License: AGPL-3
Author: Odoo Community Association (OCA), PyTech SRL
Author-email: support@odoo-community.org
Classifier: Programming Language :: Python
Classifier: Framework :: Odoo
Classifier: Framework :: Odoo :: 17.0
Classifier: License :: OSI Approved :: GNU Affero General Public License v3
